roop_custom_logger/__init__.py
roop_custom_logger/custom_logger.py
roop_custom_logger-0.0.7.dist-info/METADATA
roop_custom_logger-0.0.7.dist-info/WHEEL
roop_custom_logger-0.0.7.dist-info/top_level.txt
roop_custom_logger-0.0.7.dist-info/RECORD
